ZetcodePythonJiaochengChuyiFix1/README.md
ZetcodePythonJiaochengChuyiFix1/__init__.py
ZetcodePythonJiaochengChuyiFix1/__main__.py
ZetcodePythonJiaochengChuyiFix1/file.epub
ZetcodePythonJiaochengChuyiFix1/index.html
ZetcodePythonJiaochengChuyiFix1/css/__init__.py
ZetcodePythonJiaochengChuyiFix1/css/annotations.css
ZetcodePythonJiaochengChuyiFix1/css/main.css
ZetcodePythonJiaochengChuyiFix1/css/normalize.css
ZetcodePythonJiaochengChuyiFix1/css/popup.css
ZetcodePythonJiaochengChuyiFix1/font/__init__.py
ZetcodePythonJiaochengChuyiFix1/font/fontello.eot
ZetcodePythonJiaochengChuyiFix1/font/fontello.svg
ZetcodePythonJiaochengChuyiFix1/font/fontello.ttf
ZetcodePythonJiaochengChuyiFix1/font/fontello.woff
ZetcodePythonJiaochengChuyiFix1/img/__init__.py
ZetcodePythonJiaochengChuyiFix1/img/annotator-glyph-sprite.png
ZetcodePythonJiaochengChuyiFix1/img/annotator-icon-sprite.png
ZetcodePythonJiaochengChuyiFix1/img/apple-touch-icon.png
ZetcodePythonJiaochengChuyiFix1/img/cancelfullscreen.png
ZetcodePythonJiaochengChuyiFix1/img/close.png
ZetcodePythonJiaochengChuyiFix1/img/fullscreen.png
ZetcodePythonJiaochengChuyiFix1/img/loader.gif
ZetcodePythonJiaochengChuyiFix1/img/menu-icon.png
ZetcodePythonJiaochengChuyiFix1/img/save.png
ZetcodePythonJiaochengChuyiFix1/img/saved.png
ZetcodePythonJiaochengChuyiFix1/img/settings-s.png
ZetcodePythonJiaochengChuyiFix1/img/settings.png
ZetcodePythonJiaochengChuyiFix1/img/star.png
ZetcodePythonJiaochengChuyiFix1/js/__init__.py
ZetcodePythonJiaochengChuyiFix1/js/epub.js
ZetcodePythonJiaochengChuyiFix1/js/epub.min.js
ZetcodePythonJiaochengChuyiFix1/js/epub.min.map
ZetcodePythonJiaochengChuyiFix1/js/hooks.min.js
ZetcodePythonJiaochengChuyiFix1/js/hooks.min.map
ZetcodePythonJiaochengChuyiFix1/js/reader.js
ZetcodePythonJiaochengChuyiFix1/js/reader.js.map
ZetcodePythonJiaochengChuyiFix1/js/reader.min.js
ZetcodePythonJiaochengChuyiFix1/js/reader.min.map
ZetcodePythonJiaochengChuyiFix1/js/hooks/__init__.py
zetcode_python_jiaocheng_chuyi_fix1-2025.3.24.0.dist-info/METADATA
zetcode_python_jiaocheng_chuyi_fix1-2025.3.24.0.dist-info/WHEEL
zetcode_python_jiaocheng_chuyi_fix1-2025.3.24.0.dist-info/entry_points.txt
zetcode_python_jiaocheng_chuyi_fix1-2025.3.24.0.dist-info/top_level.txt
zetcode_python_jiaocheng_chuyi_fix1-2025.3.24.0.dist-info/RECORD
